{
  "id": 262543,
  "name": "Wavelength",
  "description": "Wavelength is Wolfgang Warsch, Alex Hague, and Justin Vickers' deceptively simple team telepathy game — a circular plastic dial conceals a scoring zone somewhere along a spectrum, and the clue-giver gives a single phrase between two opposite ideas (a Hot/Cold prompt, say) trying to land their teammates' guess on the bullseye. Funny, contemplative, and stunningly elegant. The best party-game purchase you'll make all year.",
  "yearPublished": 2019,
  "minPlayers": 2,
  "maxPlayers": 12,
  "playingTime": 45,
  "minPlayTime": 30,
  "maxPlayTime": 45,
  "minAge": 14,
  "categories": ["Party Game"],
  "mechanics": ["Communication Limits", "Cooperative Game", "Real-Time", "Team-Based Game"],
  "designers": ["Wolfgang Warsch", "Alex Hague", "Justin Vickers"],
  "artists": [],
  "publishers": ["Palm Court", "CMYK"],
  "averageRating": 7.6,
  "averageWeight": 1.3,
  "numRatings": 13000
}
